{
  "entityType" : "NOTIFICATION_RULE",
  "entity" : {
    "additionalConfig" : {
      "description" : "Send notification to tenant admins when any Rule chain or Rule node failed to start, update or stop"
    },
    "enabled" : true,
    "externalId" : null,
    "id" : {
      "entityType" : "NOTIFICATION_RULE",
      "id" : "7d5f8580-c1dd-11ef-936d-0f17ba5f8ce7"
    },
    "name" : "Rule node initialization failure",
    "recipientsConfig" : {
      "targets" : [ "7d5a7c70-c1dd-11ef-936d-0f17ba5f8ce7" ],
      "triggerType" : "RULE_ENGINE_COMPONENT_LIFECYCLE_EVENT"
    },
    "templateId" : {
      "entityType" : "NOTIFICATION_TEMPLATE",
      "id" : "7d5f3760-c1dd-11ef-936d-0f17ba5f8ce7"
    },
    "triggerConfig" : {
      "triggerType" : "RULE_ENGINE_COMPONENT_LIFECYCLE_EVENT",
      "onlyRuleChainLifecycleFailures" : true,
      "onlyRuleNodeLifecycleFailures" : true,
      "ruleChainEvents" : [ "STOPPED", "UPDATED", "STARTED" ],
      "ruleChains" : null,
      "ruleNodeEvents" : [ "STOPPED", "UPDATED", "STARTED" ],
      "trackRuleNodeEvents" : true,
      "triggerType" : "RULE_ENGINE_COMPONENT_LIFECYCLE_EVENT"
    },
    "triggerType" : "RULE_ENGINE_COMPONENT_LIFECYCLE_EVENT"
  }
}